README.md
setup.cfg
setup.py
./scripts/primer_tk
primer_tk.egg-info/PKG-INFO
primer_tk.egg-info/SOURCES.txt
primer_tk.egg-info/dependency_links.txt
primer_tk.egg-info/requires.txt
primer_tk.egg-info/top_level.txt
primer_tk.egg-info/zip-safe
src/primer_tk/__init__.py
src/primer_tk/__main__.py
src/primer_tk/analyze_pcr_output.py
src/primer_tk/analyze_pcr_output_sv.py
src/primer_tk/constants.py
src/primer_tk/core.py
src/primer_tk/genome_iterator.py
src/primer_tk/genome_iterator_sv.py
src/primer_tk/mp_class.py
src/primer_tk/mp_class_sv.py
src/primer_tk/primer_cross_hyb.py
src/primer_tk/primer_tabix.py
src/primer_tk/sequence_info.py
src/primer_tk/utils.py
test/python_tests/test_analyze_pcr_output.py
test/python_tests/test_analyze_pcr_output_sv.py
test/python_tests/test_core.py
test/python_tests/test_genome_iterator.py
test/python_tests/test_genome_iterator_sv.py
test/python_tests/test_mp_class.py
test/python_tests/test_mp_class_sv.py
test/python_tests/test_primer_cross_hyb.py
test/python_tests/test_primer_tabix.py
test/python_tests/test_sequence_info.py