Metadata-Version: 1.2
Name: primer-tk
Version: 1.0.0
Summary: A toolkit to design primers in multiplex pools and around SVs.
Home-page: https://github.com/stjude/PrimerTK
Author: Dennis Kennetz
Author-email: dennis.kennetz@stjude.org
License: Apache2.0
Download-URL: https://github.com/stjude/PrimerTK/archive/1.0.0.tar.gz
Platform: UNKNOWN
Classifier: Programming Language :: Python :: 3
Classifier: Environment :: Console
Classifier: Natural Language :: English
Classifier: Operating System :: OS Independent
Requires-Python: >=3.5.*
